{
  "name": "Auto publish workspace → YouTube + Facebook (by published_at ↑)",
  "nodes": [
    {
      "parameters": {},
      "id": "11111111-1111-4111-8111-111111111101",
      "name": "Execute workflow",
      "type": "n8n-nodes-base.manualTrigger",
      "typeVersion": 1,
      "position": [620, -140]
    },
    {
      "parameters": {
        "values": {
          "string": [
            {
              "name": "workspace",
              "value": "D:\\Downloads\\workspace\\horror_story"
            },
            {
              "name": "schedule_interval_hours",
              "value": "4"
            },
            {
              "name": "schedule_start",
              "value": ""
            }
          ]
        },
        "options": {}
      },
      "id": "11111111-1111-4111-8111-111111111102",
      "name": "1 Workspace (folder chứa các session)",
      "type": "n8n-nodes-base.set",
      "typeVersion": 1,
      "position": [620, 20]
    },
    {
      "parameters": {
        "mode": "runOnceForAllItems",
        "language": "javaScript",
        "jsCode": "// === CHỈNH MỘT LẦN: clone repo + Fanpage Facebook (không phải profile cá nhân) ===\nconst REPO_ROOT = String.raw`D:\\Nguyen-Anh-Viet\\Tutorial\\Python\\audio-to-text\\video-subtitle-translator`;\n// ID Fanpage dạng số (hoặc username trang nếu API chấp nhận). Node \"15 Facebook\" gọi Graph: POST /{PAGE_ID}/videos.\nconst FACEBOOK_PAGE_ID = 'YOUR_PAGE_ID';\n\nlet base_dir = String($json.workspace || '').trim();\nif (!base_dir) {\n  throw new Error('Cần \"workspace\": đường dẫn thư mục chứa các folder session.');\n}\nbase_dir = base_dir.replace(/[/\\\\]+$/, '');\nconst norm = base_dir.replace(/\\\\/g, '/').replace(/\\/+$/, '');\nconst log_file = `${norm}/n8n_publish_run.jsonl`;\n\nlet hours = Number($json.schedule_interval_hours);\nif (!Number.isFinite(hours) || hours <= 0) hours = 4;\nlet schedule_args = `--schedule-interval-hours ${hours}`;\nconst schedule_start = String($json.schedule_start || '').trim();\nif (schedule_start) {\n  schedule_args += schedule_start.includes(' ')\n    ? ` --schedule-start \"${schedule_start.replace(/\"/g, '')}\"`\n    : ` --schedule-start ${schedule_start}`;\n}\n\nreturn [\n  {\n    json: {\n      workspace: base_dir,\n      base_dir,\n      repo_root: REPO_ROOT,\n      log_file,\n      facebook_page_id: FACEBOOK_PAGE_ID,\n      schedule_interval_hours: hours,\n      schedule_start,\n      schedule_args,\n    },\n  },\n];"
      },
      "id": "11111111-1111-4111-8111-111111111119",
      "name": "2 Publishing config (sửa 1 lần trong Code)",
      "type": "n8n-nodes-base.code",
      "typeVersion": 2,
      "position": [620, 180]
    },
    {
      "parameters": {
        "content": "## Một cổng vào • Một cú nhấp\n\n**Lỗi** `Unrecognized node type … executeCommand`? n8n **2+** và **Cloud** thường **chặn** node này. Cần **self-host** và bật node: biến **`NODES_EXCLUDE=[]`** rồi restart (chi tiết README **§3.3**).\n\n**Mỗi lần chạy** — node **`1 Workspace`**:\n- **`workspace`**: thư mục cha các session.\n- **`schedule_interval_hours`**: khoảng cách giữa từng video (mặc định `4`).\n- **`schedule_start`**: thời điểm **video đầu tiên** (ISO-8601), ví dụ `2026-05-01T08:00:00+07:00`. Để **trống** → Python dùng `published_at` của session đầu (cùng thứ tự cũ→mới).\n\n**Một lần duy nhất**: **`2 Publishing config`** → `REPO_ROOT`, **`FACEBOOK_PAGE_ID` = ID Fanpage** (số trang bạn quản trị; **không** phải ID profile cá nhân). Node **15 Facebook** gọi API `…/{PAGE_ID}/videos` — video lên **đúng Fanpage đó**.\n\n**Facebook**: Credential **`Facebook Graph API - page token`** phải là **Page Access Token** (token của **Fanpage** / quyền đăng bài lên trang), không dùng token chỉ để đăng lên dòng thời gian cá nhân.\n\n**Thứ tự**: job theo `published_at` tăng dần; mỗi job lệch **`schedule_interval_hours`** so với job trước tính từ **`schedule_start`** (hoặc mốc mặc định).\n\n**Credentials**: `YouTube OAuth2 - publish workspace`, `Facebook Graph API - page token`.\n\n**Khác**: `N8N_RESTRICT_FILE_ACCESS_TO` nếu cần đọc video.",
        "height": 500,
        "width": 560,
        "color": 5
      },
      "id": "11111111-1111-4111-8111-111111111199",
      "name": "Hướng dẫn",
      "type": "n8n-nodes-base.stickyNote",
      "typeVersion": 1,
      "position": [60, -180]
    },
    {
      "parameters": {
        "executeOnce": true,
        "command": "=cmd /c cd /d {{ $('2 Publishing config (sửa 1 lần trong Code)').item.json.repo_root }} && python n8n-automatioin\\workflow_log_append.py {{ $('2 Publishing config (sửa 1 lần trong Code)').item.json.log_file }} workflow_start --level INFO --message export_begin_workspace={{ $('2 Publishing config (sửa 1 lần trong Code)').item.json.base_dir }}"
      },
      "id": "11111111-1111-4111-8111-111111111103",
      "name": "3 Log • start",
      "type": "n8n-nodes-base.executeCommand",
      "typeVersion": 1,
      "position": [880, 100]
    },
    {
      "parameters": {
        "executeOnce": true,
        "command": "=cmd /c cd /d {{ $json.repo_root }} && python n8n-automatioin\\export_publish_jobs.py {{ $json.base_dir }} --platform youtube --platform facebook {{ $json.schedule_args }} --pretty"
      },
      "id": "11111111-1111-4111-8111-111111111104",
      "name": "4 Export jobs (Python)",
      "type": "n8n-nodes-base.executeCommand",
      "typeVersion": 1,
      "position": [620, 340]
    },
    {
      "parameters": {
        "mode": "runOnceForAllItems",
        "language": "javaScript",
        "jsCode": "const item = $input.first().json;\nconst cfg = $('2 Publishing config (sửa 1 lần trong Code)').first().json;\nconst text = item.stdout ?? item.text ?? '';\nif (item.exitCode !== 0 && item.exitCode !== undefined) {\n  throw new Error(item.stderr || `export failed (exit ${item.exitCode})`);\n}\nconst parsed = JSON.parse(text || '{}');\nif (!Array.isArray(parsed.jobs)) {\n  throw new Error('Exporter JSON must contain a jobs array');\n}\nreturn parsed.jobs.map((job) => ({\n  json: {\n    ...job,\n    repo_root: cfg.repo_root,\n    base_dir: cfg.base_dir,\n    log_file: cfg.log_file,\n    facebook_page_id: cfg.facebook_page_id,\n  },\n}));"
      },
      "id": "11111111-1111-4111-8111-111111111105",
      "name": "5 Split jobs (+ giữ config)",
      "type": "n8n-nodes-base.code",
      "typeVersion": 2,
      "position": [620, 500]
    },
    {
      "parameters": {
        "executeOnce": false,
        "command": "=cmd /c cd /d {{ $json.repo_root }} && python n8n-automatioin\\workflow_log_append.py {{ $json.log_file }} job_begin --level INFO --message session={{ $json.session_name }}"
      },
      "id": "11111111-1111-4111-8111-111111111106",
      "name": "6 Log • job begin",
      "type": "n8n-nodes-base.executeCommand",
      "typeVersion": 1,
      "position": [620, 660]
    },
    {
      "parameters": {
        "operation": "read",
        "fileSelector": "={{ $('5 Split jobs (+ giữ config)').item.json.video_path.split(String.fromCharCode(92)).join('/') }}",
        "options": {
          "dataPropertyName": "data"
        }
      },
      "id": "11111111-1111-4111-8111-111111111107",
      "name": "7 Read video (YouTube)",
      "type": "n8n-nodes-base.readWriteFile",
      "typeVersion": 1,
      "position": [620, 820],
      "continueOnFail": true,
      "alwaysOutputData": true
    },
    {
      "parameters": {
        "mode": "runOnceForEachItem",
        "language": "javaScript",
        "jsCode": "const item = $input.item;\nif (item.json.error) {\n  throw new Error('Read video (YouTube): ' + String(item.json.error));\n}\nif (!item.binary?.data) {\n  throw new Error('Read video (YouTube): missing binary.data');\n}\nreturn item;"
      },
      "id": "11111111-1111-4111-8111-111111111108",
      "name": "8 Check read OK",
      "type": "n8n-nodes-base.code",
      "typeVersion": 2,
      "position": [620, 980]
    },
    {
      "parameters": {
        "resource": "video",
        "operation": "upload",
        "title": "={{ $('5 Split jobs (+ giữ config)').item.json.title }}",
        "regionCode": "US",
        "categoryId": "22",
        "binaryProperty": "data",
        "options": {
          "description": "={{ $('5 Split jobs (+ giữ config)').item.json.description }}",
          "privacyStatus": "private",
          "publishAt": "={{ $('5 Split jobs (+ giữ config)').item.json.scheduled_at }}",
          "tags": "={{ (($('5 Split jobs (+ giữ config)').item.json.hashtags) || []).join(',') }}"
        }
      },
      "id": "11111111-1111-4111-8111-111111111109",
      "name": "9 YouTube upload",
      "type": "n8n-nodes-base.youTube",
      "typeVersion": 1,
      "position": [620, 1140],
      "credentials": {
        "youTubeOAuth2Api": {
          "name": "YouTube OAuth2 - publish workspace"
        }
      }
    },
    {
      "parameters": {
        "mode": "runOnceForEachItem",
        "language": "javaScript",
        "jsCode": "const j = $input.item.json;\nif (j.error) {\n  throw new Error('YouTube API: ' + JSON.stringify(j.error).slice(0, 800));\n}\nif (!j.id) {\n  throw new Error('YouTube: no video id in response: ' + JSON.stringify(j).slice(0, 800));\n}\nreturn $input.item;"
      },
      "id": "11111111-1111-4111-8111-111111111110",
      "name": "10 Check YouTube OK",
      "type": "n8n-nodes-base.code",
      "typeVersion": 2,
      "position": [620, 1300]
    },
    {
      "parameters": {
        "executeOnce": false,
        "command": "=cmd /c cd /d {{ $('5 Split jobs (+ giữ config)').item.json.repo_root }} && python n8n-automatioin\\mark_publish_result.py \"{{ $('5 Split jobs (+ giữ config)').item.json.session_folder }}\" --platform youtube --remote-id {{ $json.id }} --url https://www.youtube.com/watch?v={{ $json.id }} --scheduled-at \"{{ $('5 Split jobs (+ giữ config)').item.json.scheduled_at }}\""
      },
      "id": "11111111-1111-4111-8111-111111111112",
      "name": "11 Mark YouTube đã đăng",
      "type": "n8n-nodes-base.executeCommand",
      "typeVersion": 1,
      "position": [620, 1460]
    },
    {
      "parameters": {
        "executeOnce": false,
        "command": "=cmd /c cd /d {{ $('5 Split jobs (+ giữ config)').item.json.repo_root }} && python n8n-automatioin\\workflow_log_append.py {{ $('5 Split jobs (+ giữ config)').item.json.log_file }} youtube_ok --level INFO --message video_id={{ $('9 YouTube upload').item.json.id }} session={{ $('5 Split jobs (+ giữ config)').item.json.session_name }}"
      },
      "id": "11111111-1111-4111-8111-111111111111",
      "name": "12 Log • YouTube OK",
      "type": "n8n-nodes-base.executeCommand",
      "typeVersion": 1,
      "position": [620, 1620]
    },
    {
      "parameters": {
        "operation": "read",
        "fileSelector": "={{ $('5 Split jobs (+ giữ config)').item.json.video_path.split(String.fromCharCode(92)).join('/') }}",
        "options": {
          "dataPropertyName": "data"
        }
      },
      "id": "11111111-1111-4111-8111-111111111113",
      "name": "13 Read video (Facebook)",
      "type": "n8n-nodes-base.readWriteFile",
      "typeVersion": 1,
      "position": [620, 1780],
      "continueOnFail": true,
      "alwaysOutputData": true
    },
    {
      "parameters": {
        "mode": "runOnceForEachItem",
        "language": "javaScript",
        "jsCode": "const item = $input.item;\nif (item.json.error) {\n  throw new Error('Read video (Facebook): ' + String(item.json.error));\n}\nif (!item.binary?.data) {\n  throw new Error('Read video (Facebook): missing binary.data');\n}\nreturn item;"
      },
      "id": "11111111-1111-4111-8111-111111111114",
      "name": "14 Check read OK • FB",
      "type": "n8n-nodes-base.code",
      "typeVersion": 2,
      "position": [620, 1940]
    },
    {
      "parameters": {
        "hostUrl": "graph-video.facebook.com",
        "httpRequestMethod": "POST",
        "graphApiVersion": "v21.0",
        "node": "={{ $('5 Split jobs (+ giữ config)').item.json.facebook_page_id }}",
        "edge": "videos",
        "sendBinaryData": true,
        "binaryPropertyName": "source:data",
        "options": {
          "queryParameters": {
            "parameter": [
              {
                "name": "description",
                "value": "={{ $('5 Split jobs (+ giữ config)').item.json.description }}"
              }
            ]
          }
        }
      },
      "id": "11111111-1111-4111-8111-111111111115",
      "name": "15 Facebook • upload video",
      "type": "n8n-nodes-base.facebookGraphApi",
      "typeVersion": 1,
      "position": [620, 2100],
      "credentials": {
        "facebookGraphApi": {
          "name": "Facebook Graph API - page token"
        }
      },
      "continueOnFail": true,
      "alwaysOutputData": true
    },
    {
      "parameters": {
        "mode": "runOnceForEachItem",
        "language": "javaScript",
        "jsCode": "const j = $input.item.json;\nif (j.error) {\n  throw new Error('Facebook Graph: ' + JSON.stringify(j.error).slice(0, 800));\n}\nif (!j.id) {\n  throw new Error('Facebook: no id in response: ' + JSON.stringify(j).slice(0, 800));\n}\nreturn $input.item;"
      },
      "id": "11111111-1111-4111-8111-111111111116",
      "name": "16 Check Facebook OK",
      "type": "n8n-nodes-base.code",
      "typeVersion": 2,
      "position": [620, 2260]
    },
    {
      "parameters": {
        "executeOnce": false,
        "command": "=cmd /c cd /d {{ $('5 Split jobs (+ giữ config)').item.json.repo_root }} && python n8n-automatioin\\mark_publish_result.py \"{{ $('5 Split jobs (+ giữ config)').item.json.session_folder }}\" --platform facebook --remote-id {{ $json.id }} --url https://www.facebook.com/watch/?v={{ $json.id }} --scheduled-at \"{{ $('5 Split jobs (+ giữ config)').item.json.scheduled_at }}\""
      },
      "id": "11111111-1111-4111-8111-111111111118",
      "name": "17 Mark Facebook đã đăng",
      "type": "n8n-nodes-base.executeCommand",
      "typeVersion": 1,
      "position": [620, 2420]
    },
    {
      "parameters": {
        "executeOnce": false,
        "command": "=cmd /c cd /d {{ $('5 Split jobs (+ giữ config)').item.json.repo_root }} && python n8n-automatioin\\workflow_log_append.py {{ $('5 Split jobs (+ giữ config)').item.json.log_file }} facebook_ok --level INFO --message fb_video_id={{ $('15 Facebook • upload video').item.json.id }} session={{ $('5 Split jobs (+ giữ config)').item.json.session_name }}"
      },
      "id": "11111111-1111-4111-8111-111111111117",
      "name": "18 Log • Facebook OK",
      "type": "n8n-nodes-base.executeCommand",
      "typeVersion": 1,
      "position": [620, 2580]
    }
  ],
  "connections": {
    "Execute workflow": {
      "main": [
        [
          {
            "node": "1 Workspace (folder chứa các session)",
            "type": "main",
            "index": 0
          }
        ]
      ]
    },
    "1 Workspace (folder chứa các session)": {
      "main": [
        [
          {
            "node": "2 Publishing config (sửa 1 lần trong Code)",
            "type": "main",
            "index": 0
          }
        ]
      ]
    },
    "2 Publishing config (sửa 1 lần trong Code)": {
      "main": [
        [
          {
            "node": "3 Log • start",
            "type": "main",
            "index": 0
          },
          {
            "node": "4 Export jobs (Python)",
            "type": "main",
            "index": 0
          }
        ]
      ]
    },
    "4 Export jobs (Python)": {
      "main": [
        [
          {
            "node": "5 Split jobs (+ giữ config)",
            "type": "main",
            "index": 0
          }
        ]
      ]
    },
    "5 Split jobs (+ giữ config)": {
      "main": [
        [
          {
            "node": "6 Log • job begin",
            "type": "main",
            "index": 0
          }
        ]
      ]
    },
    "6 Log • job begin": {
      "main": [
        [
          {
            "node": "7 Read video (YouTube)",
            "type": "main",
            "index": 0
          }
        ]
      ]
    },
    "7 Read video (YouTube)": {
      "main": [
        [
          {
            "node": "8 Check read OK",
            "type": "main",
            "index": 0
          }
        ]
      ]
    },
    "8 Check read OK": {
      "main": [
        [
          {
            "node": "9 YouTube upload",
            "type": "main",
            "index": 0
          }
        ]
      ]
    },
    "9 YouTube upload": {
      "main": [
        [
          {
            "node": "10 Check YouTube OK",
            "type": "main",
            "index": 0
          }
        ]
      ]
    },
    "10 Check YouTube OK": {
      "main": [
        [
          {
            "node": "11 Mark YouTube đã đăng",
            "type": "main",
            "index": 0
          }
        ]
      ]
    },
    "11 Mark YouTube đã đăng": {
      "main": [
        [
          {
            "node": "12 Log • YouTube OK",
            "type": "main",
            "index": 0
          }
        ]
      ]
    },
    "12 Log • YouTube OK": {
      "main": [
        [
          {
            "node": "13 Read video (Facebook)",
            "type": "main",
            "index": 0
          }
        ]
      ]
    },
    "13 Read video (Facebook)": {
      "main": [
        [
          {
            "node": "14 Check read OK • FB",
            "type": "main",
            "index": 0
          }
        ]
      ]
    },
    "14 Check read OK • FB": {
      "main": [
        [
          {
            "node": "15 Facebook • upload video",
            "type": "main",
            "index": 0
          }
        ]
      ]
    },
    "15 Facebook • upload video": {
      "main": [
        [
          {
            "node": "16 Check Facebook OK",
            "type": "main",
            "index": 0
          }
        ]
      ]
    },
    "16 Check Facebook OK": {
      "main": [
        [
          {
            "node": "17 Mark Facebook đã đăng",
            "type": "main",
            "index": 0
          }
        ]
      ]
    },
    "17 Mark Facebook đã đăng": {
      "main": [
        [
          {
            "node": "18 Log • Facebook OK",
            "type": "main",
            "index": 0
          }
        ]
      ]
    }
  },
  "active": false,
  "settings": {
    "executionOrder": "v1"
  },
  "meta": {
    "templateCredsSetupCompleted": false
  },
  "tags": []
}
